video_browser/__init__.py
video_browser/__main__.py
video_browser/gui.py
video_browser-1.0.dist-info/LICENSE
video_browser-1.0.dist-info/METADATA
video_browser-1.0.dist-info/WHEEL
video_browser-1.0.dist-info/top_level.txt
video_browser-1.0.dist-info/RECORD
