Metadata-Version: 2.1
Name: video-browser
Version: 1.0
Summary: Browse video frames and apply basic transformations.
Home-page: https://gitlab.com/Dominik1123/video-browser
Author: Dominik Vilsmeier
Author-email: d.vilsmeier@gsi.de
License: GPL-3.0
Keywords: video,display,frames
Platform: UNKNOWN
Classifier: Development Status :: 4 - Beta
Classifier: Intended Audience :: End Users/Desktop
Classifier: License :: OSI Approved :: GNU General Public License v3 or later (GPLv3+)
Classifier: Programming Language :: Python :: 3.7
Classifier: Programming Language :: Python :: 3.8
Classifier: Topic :: Multimedia :: Video :: Display
Requires-Python: >=3.7
Requires-Dist: arguable
Requires-Dist: matplotlib
Requires-Dist: numpy
Requires-Dist: opencv-python
Requires-Dist: PyQt5
